stig_parser/__init__.py
stig_parser/stig_parser.py
stig_parser/version.py
stig_parser-1.1.1.dist-info/LICENSE
stig_parser-1.1.1.dist-info/METADATA
stig_parser-1.1.1.dist-info/WHEEL
stig_parser-1.1.1.dist-info/top_level.txt
stig_parser-1.1.1.dist-info/RECORD
