Metadata-Version: 2.1
Name: stig-parser
Version: 1.1.1
Summary: A Python module to parse DISA STIG (XCCDF) Files
Home-page: https://github.com/pkeech/stig_parser
Author: Peter Keech
Author-email: peter.a.keech@gmail.com
License: MIT
Classifier: Programming Language :: Python :: 3.8
Classifier: Programming Language :: Python :: 3.9
Classifier: License :: OSI Approved :: MIT License
Classifier: Operating System :: OS Independent
Requires-Python: >=3.8
License-File: LICENSE
Requires-Dist: xmltodict
